FluentUI/__init__.py
FluentUI/qml/FluentUI/fluentuiplugin.dll
FluentUI/qml/FluentUI/plugins.qmltypes
FluentUI/qml/FluentUI/qmldir
FluentUI/qml/FluentUI/Controls/FluAcrylic.qml
FluentUI/qml/FluentUI/Controls/FluAppBar.qml
FluentUI/qml/FluentUI/Controls/FluArea.qml
FluentUI/qml/FluentUI/Controls/FluAutoSuggestBox.qml
FluentUI/qml/FluentUI/Controls/FluBadge.qml
FluentUI/qml/FluentUI/Controls/FluBreadcrumbBar.qml
FluentUI/qml/FluentUI/Controls/FluButton.qml
FluentUI/qml/FluentUI/Controls/FluCalendarPicker.qml
FluentUI/qml/FluentUI/Controls/FluCalendarView.qml
FluentUI/qml/FluentUI/Controls/FluCarousel.qml
FluentUI/qml/FluentUI/Controls/FluChart.qml
FluentUI/qml/FluentUI/Controls/FluCheckBox.qml
FluentUI/qml/FluentUI/Controls/FluClip.qml
FluentUI/qml/FluentUI/Controls/FluColorPicker.qml
FluentUI/qml/FluentUI/Controls/FluColorView.qml
FluentUI/qml/FluentUI/Controls/FluComboBox.qml
FluentUI/qml/FluentUI/Controls/FluContentDialog.qml
FluentUI/qml/FluentUI/Controls/FluContentPage.qml
FluentUI/qml/FluentUI/Controls/FluControl.qml
FluentUI/qml/FluentUI/Controls/FluCopyableText.qml
FluentUI/qml/FluentUI/Controls/FluDatePicker.qml
FluentUI/qml/FluentUI/Controls/FluDivider.qml
FluentUI/qml/FluentUI/Controls/FluDropDownButton.qml
FluentUI/qml/FluentUI/Controls/FluExpander.qml
FluentUI/qml/FluentUI/Controls/FluFilledButton.qml
FluentUI/qml/FluentUI/Controls/FluFlipView.qml
FluentUI/qml/FluentUI/Controls/FluFocusRectangle.qml
FluentUI/qml/FluentUI/Controls/FluIcon.qml
FluentUI/qml/FluentUI/Controls/FluIconButton.qml
FluentUI/qml/FluentUI/Controls/FluImage.qml
FluentUI/qml/FluentUI/Controls/FluImageButton.qml
FluentUI/qml/FluentUI/Controls/FluInfoBar.qml
FluentUI/qml/FluentUI/Controls/FluItemDelegate.qml
FluentUI/qml/FluentUI/Controls/FluLoader.qml
FluentUI/qml/FluentUI/Controls/FluLoadingButton.qml
FluentUI/qml/FluentUI/Controls/FluMenu.qml
FluentUI/qml/FluentUI/Controls/FluMenuBar.qml
FluentUI/qml/FluentUI/Controls/FluMenuBarItem.qml
FluentUI/qml/FluentUI/Controls/FluMenuItem.qml
PySide6_FluentUI_QML-1.6.7.dist-info/METADATA
PySide6_FluentUI_QML-1.6.7.dist-info/WHEEL
PySide6_FluentUI_QML-1.6.7.dist-info/top_level.txt
PySide6_FluentUI_QML-1.6.7.dist-info/RECORD
