Metadata-Version: 2.1
Name: PySide6-FluentUI-QML
Version: 1.6.7
Summary: A fluent design qml library based on PySide6
Home-page: https://github.com/zhuzichu520/FluentUI
Author: ZhuZiChu
Author-email: zhuzichu520@outlook.com
License: MIT
Keywords: pyside fluent qml
Classifier: Programming Language :: Python :: 3
Requires-Dist: PySide6 >=6.6.1
